safeopt/__init__.py
safeopt/gp_opt.py
safeopt/swarm.py
safeopt/utilities.py
safeopt-0.16.dist-info/LICENSE
safeopt-0.16.dist-info/METADATA
safeopt-0.16.dist-info/WHEEL
safeopt-0.16.dist-info/top_level.txt
safeopt-0.16.dist-info/RECORD
