Metadata-Version: 2.1
Name: safeopt
Version: 0.16
Summary: Safe Bayesian optimization
Home-page: https://github.com/befelix/SafeOpt
Author: Felix Berkenkamp
Author-email: befelix@inf.ethz.ch
License: MIT
Keywords: Bayesian optimization,Safety
Platform: UNKNOWN
Classifier: Development Status :: 4 - Beta
Classifier: License :: OSI Approved :: MIT License
Classifier: Programming Language :: Python :: 2
Classifier: Programming Language :: Python :: 2.7
Classifier: Programming Language :: Python :: 3
Classifier: Programming Language :: Python :: 3.5
Requires-Dist: GPy (>=0.8)
Requires-Dist: numpy (<2.0,>=1.7)
Requires-Dist: scipy (>=0.12)
Requires-Dist: matplotlib (>=1.3)
Requires-Dist: future
